songsync/__init__.py
songsync/lang_helpers.py
songsync/songsync.py
songsync/sp_helpers.py
songsync/yt_helpers.py
songsync-0.1.4.dist-info/LICENSE
songsync-0.1.4.dist-info/METADATA
songsync-0.1.4.dist-info/WHEEL
songsync-0.1.4.dist-info/RECORD
