Metadata-Version: 2.1
Name: songsync
Version: 0.1.4
Summary: Convert YouTube playlists to Spotify playlists
Home-page: https://github.com/pianobin/songsync
Author: pianobin
Author-email: shoji@pianobin.com
Requires-Python: >=3.11,<4.0
Classifier: Programming Language :: Python :: 3
Classifier: Programming Language :: Python :: 3.11
Classifier: Programming Language :: Python :: 3.12
Requires-Dist: langid (>=1.1.6,<2.0.0)
Requires-Dist: requests (>=2.31.0,<3.0.0)
Requires-Dist: spotipy (>=2.23.0,<3.0.0)
Requires-Dist: ytmusicapi (>=1.3.2,<2.0.0)
Project-URL: Repository, https://github.com/pianobin/songsync
